scoras/__init__.py
scoras/a2a.py
scoras/agents.py
scoras/contextual_rag.py
scoras/core.py
scoras/mcp.py
scoras/minimal_test.py
scoras/rag.py
scoras/retriever.py
scoras/tools.py
scoras/scoring/__init__.py
scoras-0.3.4.dist-info/licenses/LICENSE
scoras-0.3.4.dist-info/METADATA
scoras-0.3.4.dist-info/WHEEL
scoras-0.3.4.dist-info/top_level.txt
scoras-0.3.4.dist-info/RECORD
