Metadata-Version: 2.4
Name: scoras
Version: 0.3.4
Summary: Intelligent Agent Framework with Complexity Scoring
Home-page: https://github.com/scorastecnologialtda/scoras
Author: Anderson L. Amaral
Author-email: "Anderson L. Amaral" <luis.anderson.sp@gmail.com>
License: MIT
Project-URL: Homepage, https://github.com/scorastecnologialtda/scoras
Project-URL: Documentation, https://github.com/scorastecnologialtda/scoras/blob/main/README.md
Project-URL: Bug Tracker, https://github.com/scorastecnologialtda/scoras/issues
Classifier: Programming Language :: Python :: 3
Classifier: Programming Language :: Python :: 3.8
Classifier: Programming Language :: Python :: 3.9
Classifier: Programming Language :: Python :: 3.10
Classifier: Programming Language :: Python :: 3.11
Classifier: License :: OSI Approved :: MIT License
Classifier: Operating System :: OS Independent
Classifier: Topic :: Scientific/Engineering :: Artificial Intelligence
Classifier: Intended Audience :: Developers
Classifier: Intended Audience :: Science/Research
Requires-Python: >=3.8
License-File: LICENSE
Requires-Dist: pydantic>=2.0.0
Requires-Dist: httpx>=0.24.0
Requires-Dist: numpy>=1.20.0
Requires-Dist: typing-extensions>=4.0.0
Requires-Dist: asyncio>=3.4.3
Requires-Dist: aiohttp>=3.8.0
Provides-Extra: dev
Requires-Dist: pytest>=7.0.0; extra == "dev"
Requires-Dist: pytest-asyncio>=0.20.0; extra == "dev"
Requires-Dist: black>=23.0.0; extra == "dev"
Requires-Dist: isort>=5.12.0; extra == "dev"
Requires-Dist: mypy>=1.0.0; extra == "dev"
Provides-Extra: openai
Requires-Dist: openai>=1.0.0; extra == "openai"
Provides-Extra: anthropic
Requires-Dist: anthropic>=0.5.0; extra == "anthropic"
Dynamic: author
Dynamic: home-page
Dynamic: license-file
Dynamic: requires-python
